pnap_audit_api/__init__.py
pnap_audit_api/api_client.py
pnap_audit_api/api_response.py
pnap_audit_api/configuration.py
pnap_audit_api/exceptions.py
pnap_audit_api/py.typed
pnap_audit_api/rest.py
pnap_audit_api/version.py
pnap_audit_api/api/__init__.py
pnap_audit_api/api/events_api.py
pnap_audit_api/models/__init__.py
pnap_audit_api/models/error.py
pnap_audit_api/models/event.py
pnap_audit_api/models/user_info.py
pnap_audit_api-2.0.4.dist-info/METADATA
pnap_audit_api-2.0.4.dist-info/WHEEL
pnap_audit_api-2.0.4.dist-info/top_level.txt
pnap_audit_api-2.0.4.dist-info/RECORD
